bootstrap/__init__.py
bootstrap/__main__.py
bootstrap/artifacts.py
bootstrap/config_loader.py
bootstrap/constants.py
bootstrap/git_ops.py
bootstrap/install.py
bootstrap/orchestrator.py
bootstrap/payload.py
bootstrap/prompts.py
bootstrap/py.typed
bootstrap/runner.py
bootstrap/telemetry.py
flywheel_bootstrap-0.1.9.202601311458.dist-info/METADATA
flywheel_bootstrap-0.1.9.202601311458.dist-info/WHEEL
flywheel_bootstrap-0.1.9.202601311458.dist-info/entry_points.txt
flywheel_bootstrap-0.1.9.202601311458.dist-info/RECORD
