Metadata-Version: 2.4
Name: flywheel-bootstrap
Version: 0.1.9.202601311458
Summary: Bootstrap runner for Flywheel provisioned GPU instances
Project-URL: Homepage, http://paradigma.inc/
Author: Paradigma Labs
License: MIT
Keywords: bootstrap,flywheel,gpu,machine-learning,ml
Classifier: Development Status :: 4 - Beta
Classifier: Intended Audience :: Developers
Classifier: License :: OSI Approved :: MIT License
Classifier: Programming Language :: Python :: 3.11
Classifier: Programming Language :: Python :: 3.12
Requires-Python: >=3.11
